blogs/__init__.py
blogs/admin.py
blogs/apps.py
blogs/mixins.py
blogs/models.py
blogs/settings.py
blogs/urls.py
blogs/views.py
blogs/migrations/0001_initial.py
blogs/migrations/0002_auto_20181106_1719.py
blogs/migrations/__init__.py
blogs/static/css/beagle-theme.min.css
blogs/static/css/blogs-common.css
blogs/templates/django-blogs/base.html
blogs/templates/django-blogs/blog.html
blogs/templates/django-blogs/drafts.html
blogs/templates/django-blogs/editor.html
blogs/templates/django-blogs/footer.html
blogs/templates/django-blogs/google_analytics.html
blogs/templates/django-blogs/home.html
djangoblogs-0.2.0.dist-info/LICENSE
djangoblogs-0.2.0.dist-info/METADATA
djangoblogs-0.2.0.dist-info/WHEEL
djangoblogs-0.2.0.dist-info/top_level.txt
djangoblogs-0.2.0.dist-info/RECORD
