Metadata-Version: 2.1
Name: djangoblogs
Version: 0.2.0
Summary: Django blogging with medium style editor
Home-page: https://github.com/arjunsinghy96/djangoblogs
Author: Arjun Singh Yadav
Author-email: arjunsinghy96@gmail.com
License: MIT
Keywords: django blogs medium blog
Platform: UNKNOWN
Classifier: Intended Audience :: Developers
Classifier: License :: OSI Approved :: MIT License
Classifier: Programming Language :: Python :: 3.5
Classifier: Programming Language :: Python :: 3.6
Classifier: Framework :: Django :: 2.0
Classifier: Framework :: Django :: 2.1
Requires-Dist: django (>=2.0)
